nanpa_lookup/__init__.py
nanpa_lookup/database.sqlite
nanpa_lookup/lookup.py
nanpa_lookup-1.0.1.dist-info/LICENSE
nanpa_lookup-1.0.1.dist-info/METADATA
nanpa_lookup-1.0.1.dist-info/WHEEL
nanpa_lookup-1.0.1.dist-info/entry_points.txt
nanpa_lookup-1.0.1.dist-info/top_level.txt
nanpa_lookup-1.0.1.dist-info/RECORD
