Metadata-Version: 2.1
Name: nanpa-lookup
Version: 1.0.1
Summary: Lookup numbers in NANPA database
Home-page: https://github.com/evidlo/nanpa_lookup
Author: Evan Widloski
Author-email: evan_ex@widloski.com
License: GPL3
Platform: UNKNOWN
License-File: LICENSE
